jupyter_telemetry/__init__.py
jupyter_telemetry/__version__.py
jupyter_telemetry/eventlog.py
jupyter_telemetry/traits.py
jupyter_telemetry-0.0.5.dist-info/LICENSE
jupyter_telemetry-0.0.5.dist-info/METADATA
jupyter_telemetry-0.0.5.dist-info/WHEEL
jupyter_telemetry-0.0.5.dist-info/top_level.txt
jupyter_telemetry-0.0.5.dist-info/RECORD
