Metadata-Version: 2.1
Name: jupyter-telemetry
Version: 0.0.5
Summary: Jupyter telemetry library
Home-page: http://jupyter.org
Author: Jupyter Development Team
Author-email: jupyter@googlegroups.com
License: BSD
Keywords: Jupyter,JupyterLab
Platform: Linux
Platform: Mac OS X
Platform: Windows
Classifier: Intended Audience :: Developers
Classifier: Intended Audience :: System Administrators
Classifier: Intended Audience :: Science/Research
Classifier: License :: OSI Approved :: BSD License
Classifier: Programming Language :: Python
Classifier: Programming Language :: Python :: 3
Requires-Python: >=3.5
Requires-Dist: jsonschema
Requires-Dist: python-json-logger
Requires-Dist: traitlets
Requires-Dist: ruamel.yaml
